knockofforigins/__init__.py
knockofforigins/data_gen.py
knockofforigins/decompose.py
knockofforigins/evaluation.py
knockofforigins/gram_matrix.py
knockofforigins/knockoff.py
knockofforigins/knockoff_construct.py
knockofforigins/lasso.py
knockofforigins/plots.py
knockofforigins/testatistics.py
knockofforigins/utils.py
knockofforigins-0.1.4.dist-info/LICENSE
knockofforigins-0.1.4.dist-info/METADATA
knockofforigins-0.1.4.dist-info/WHEEL
knockofforigins-0.1.4.dist-info/RECORD
