Metadata-Version: 2.1
Name: KnockoffOrigins
Version: 0.1.4
Summary: This repository is dedicated to implementing the methodologies from the 2015 paper "False Discovery Rate via Knockoffs". It provides code for generating knockoff features and applying selection procedures. The aim is to help users understand and apply the knockoff method for feature selection. Please refer to the original paper for a complete understanding.
Home-page: https://github.com/jrazi/KnockoffOrigins
License: MIT
Author: Javad Razi
Author-email: j.razi@outlook.com
Requires-Python: >=3.9,<4.0
Classifier: License :: OSI Approved :: MIT License
Classifier: Programming Language :: Python :: 3
Classifier: Programming Language :: Python :: 3.9
Classifier: Programming Language :: Python :: 3.10
Classifier: Programming Language :: Python :: 3.11
Classifier: Programming Language :: Python :: 3.12
Requires-Dist: matplotlib (>=3.8.4,<4.0.0)
Requires-Dist: pandas (>=2.2.2,<3.0.0)
Requires-Dist: scikit-learn (>=1.4.2,<2.0.0)
Requires-Dist: scipy (>=1.13.0,<2.0.0)
Requires-Dist: seaborn (>=0.13.2,<0.14.0)
Requires-Dist: statsmodels (>=0.14.2,<0.15.0)
Project-URL: Repository, https://github.com/jrazi/KnockoffOrigins
